Metadata-Version: 1.1
Name: SPAS
Version: 0.1
Summary: Single-Page App Server
Home-page: https://github.com/rshk/spas
Author: Samuele Santi
Author-email: contact-github@hackzine.org
License: BSD License
Platform: UNKNOWN
Classifier: License :: OSI Approved :: BSD License
Classifier: Programming Language :: Python :: 3.5
Classifier: Programming Language :: Python :: 3 :: Only
